seinfeld_laugh_corpus
