Metadata-Version: 1.0
Name: seinfeld-laugh-corpus
Version: 1.0.13
Summary: A humor annotated corpus of Seinfeld episodes.
Home-page: https://github.com/ranyadshalom/seinfeld_laugh_corpus
Author: Ran Yad-Shalom, Yoav Goldberg
Author-email: ranyadshalom@gmail.com
License: MIT
Platform: UNKNOWN
